scope/__init__.py
scope/cli.py
scope/models.py
scope/scope.py
scope_coupler-0.2.0.dist-info/AUTHORS.rst
scope_coupler-0.2.0.dist-info/LICENSE
scope_coupler-0.2.0.dist-info/METADATA
scope_coupler-0.2.0.dist-info/WHEEL
scope_coupler-0.2.0.dist-info/entry_points.txt
scope_coupler-0.2.0.dist-info/top_level.txt
scope_coupler-0.2.0.dist-info/RECORD
