Metadata-Version: 2.1
Name: scope-coupler
Version: 0.2.0
Summary: Scope is an offline, script based coupler for Earth System Models
Home-page: https://gitlab.awi.de/pgierz/scope
Author: Paul Gierz
Author-email: pgierz@awi.de
License: GNU General Public License v3
Keywords: scope
Platform: UNKNOWN
Classifier: Development Status :: 2 - Pre-Alpha
Classifier: Intended Audience :: Developers
Classifier: License :: OSI Approved :: GNU General Public License v3 (GPLv3)
Classifier: Natural Language :: English
Classifier: Programming Language :: Python :: 3.6
Classifier: Programming Language :: Python :: 3.7
Classifier: Programming Language :: Python :: 3.8
Classifier: Programming Language :: Python :: 3.9
Requires-Dist: Click (>=6.0)
Requires-Dist: pyyaml
Requires-Dist: jinja2
Requires-Dist: loguru
